plantuml_sequence/__init__.py
plantuml_sequence/diagram.py
plantuml_sequence/py.typed
plantuml_sequence/utils.py
plantuml_sequence-0.5.1.dist-info/METADATA
plantuml_sequence-0.5.1.dist-info/WHEEL
plantuml_sequence-0.5.1.dist-info/licenses/LICENSE
plantuml_sequence-0.5.1.dist-info/RECORD
