Metadata-Version: 2.4
Name: plantuml-sequence
Version: 0.5.1
Summary: Create PlantUML sequence diagrams programmatically from Python
Project-URL: Homepage, https://github.com/jonasehrlich/plantuml-sequence
Project-URL: Repository, https://github.com/jonasehrlich/plantuml-sequence
Project-URL: Documentation, https://plantuml-sequence.readthedocs.io
Author-email: Jonas Ehrlich <jonas.ehrlich@gmail.com>
License-Expression: MIT
License-File: LICENSE
Keywords: diagram,plantuml
Requires-Python: >=3.10
Requires-Dist: typing-extensions>=4.15.0
